udata_analysis_service/.env.sample
udata_analysis_service/__init__.py
udata_analysis_service/background_tasks.py
udata_analysis_service/cli.py
udata_analysis_service/consumer.py
udata_analysis_service/utils/__init__.py
udata_analysis_service/utils/kafka.py
udata_analysis_service-0.0.1.dev53.dist-info/entry_points.txt
udata_analysis_service-0.0.1.dev53.dist-info/WHEEL
udata_analysis_service-0.0.1.dev53.dist-info/METADATA
udata_analysis_service-0.0.1.dev53.dist-info/RECORD
