Metadata-Version: 2.1
Name: udata-analysis-service
Version: 0.0.1.dev53
Summary: 
License: MIT
Author: Etalab
Requires-Python: >=3.9,<4.0
Classifier: License :: OSI Approved :: MIT License
Classifier: Programming Language :: Python :: 3
Classifier: Programming Language :: Python :: 3.10
Classifier: Programming Language :: Python :: 3.9
Requires-Dist: boto3 (>=1.21.21,<1.22.0)
Requires-Dist: celery (>=5.2.3,<5.3.0)
Requires-Dist: click (>=8.0.4,<8.1.0)
Requires-Dist: csv-detective (>=0.4.5,<0.5.0)
Requires-Dist: flake8 (>=4.0.1,<4.1.0)
Requires-Dist: flit (>=3.6.0,<3.7.0)
Requires-Dist: kafka-python (>=2.0.2,<2.1.0)
Requires-Dist: python-dotenv (>=0.19.2,<0.20.0)
Requires-Dist: redis (>=4.1.4,<4.2.0)
Requires-Dist: requests (>=2.27.1,<2.28.0)
Requires-Dist: udata_event_service (>=0.0.8,<0.1.0)
